{
  "type": "excalidraw",
  "version": 2,
  "source": "https://github.com/yinchengwang/c--code-book",
  "elements": [
    {
      "id": "title",
      "type": "text",
      "x": 280,
      "y": 30,
      "text": "Raft 领导者选举时序图",
      "fontSize": 32,
      "fontFamily": 1,
      "textAlign": "center",
      "verticalAlign": "middle",
      "strokeColor": "#1a1a1a",
      "backgroundColor": "transparent"
    },
    {
      "id": "box_node1",
      "type": "rectangle",
      "x": 50,
      "y": 100,
      "width": 100,
      "height": 40,
      "fillStyle": "solid",
      "fillColor": "#ffd43b",
      "strokeColor": "#1a1a1a",
      "strokeWidth": 2
    },
    {
      "id": "text_node1",
      "type": "text",
      "x": 100,
      "y": 120,
      "text": "Node-A (C)",
      "fontSize": 14,
      "fontFamily": 1,
      "textAlign": "center",
      "verticalAlign": "middle",
      "strokeColor": "#1a1a1a",
      "backgroundColor": "transparent"
    },
    {
      "id": "box_node2",
      "type": "rectangle",
      "x": 200,
      "y": 100,
      "width": 100,
      "height": 40,
      "fillStyle": "solid",
      "fillColor": "#74c0fc",
      "strokeColor": "#1a1a1a",
      "strokeWidth": 2
    },
    {
      "id": "text_node2",
      "type": "text",
      "x": 250,
      "y": 120,
      "text": "Node-B (F)",
      "fontSize": 14,
      "fontFamily": 1,
      "textAlign": "center",
      "verticalAlign": "middle",
      "strokeColor": "#1a1a1a",
      "backgroundColor": "transparent"
    },
    {
      "id": "box_node3",
      "type": "rectangle",
      "x": 350,
      "y": 100,
      "width": 100,
      "height": 40,
      "fillStyle": "solid",
      "fillColor": "#74c0fc",
      "strokeColor": "#1a1a1a",
      "strokeWidth": 2
    },
    {
      "id": "text_node3",
      "type": "text",
      "x": 400,
      "y": 120,
      "text": "Node-C (F)",
      "fontSize": 14,
      "fontFamily": 1,
      "textAlign": "center",
      "verticalAlign": "middle",
      "strokeColor": "#1a1a1a",
      "backgroundColor": "transparent"
    },
    {
      "id": "box_node4",
      "type": "rectangle",
      "x": 500,
      "y": 100,
      "width": 100,
      "height": 40,
      "fillStyle": "solid",
      "fillColor": "#74c0fc",
      "strokeColor": "#1a1a1a",
      "strokeWidth": 2
    },
    {
      "id": "text_node4",
      "type": "text",
      "x": 550,
      "y": 120,
      "text": "Node-D (F)",
      "fontSize": 14,
      "fontFamily": 1,
      "textAlign": "center",
      "verticalAlign": "middle",
      "strokeColor": "#1a1a1a",
      "backgroundColor": "transparent"
    },
    {
      "id": "line1",
      "type": "line",
      "x": 100,
      "y": 140,
      "points": [[0, 0], [0, 380]],
      "strokeColor": "#666666",
      "strokeWidth": 1
    },
    {
      "id": "line2",
      "type": "line",
      "x": 250,
      "y": 140,
      "points": [[0, 0], [0, 380]],
      "strokeColor": "#666666",
      "strokeWidth": 1
    },
    {
      "id": "line3",
      "type": "line",
      "x": 400,
      "y": 140,
      "points": [[0, 0], [0, 380]],
      "strokeColor": "#666666",
      "strokeWidth": 1
    },
    {
      "id": "line4",
      "type": "line",
      "x": 550,
      "y": 140,
      "points": [[0, 0], [0, 380]],
      "strokeColor": "#666666",
      "strokeWidth": 1
    },
    {
      "id": "timeout_box",
      "type": "rectangle",
      "x": 60,
      "y": 160,
      "width": 80,
      "height": 30,
      "fillStyle": "solid",
      "fillColor": "#e03131",
      "strokeColor": "#1a1a1a",
      "strokeWidth": 2
    },
    {
      "id": "text_timeout",
      "type": "text",
      "x": 100,
      "y": 175,
      "text": "选举超时",
      "fontSize": 11,
      "fontFamily": 1,
      "textAlign": "center",
      "verticalAlign": "middle",
      "strokeColor": "#ffffff",
      "backgroundColor": "transparent"
    },
    {
      "id": "step1",
      "type": "rectangle",
      "x": 60,
      "y": 200,
      "width": 80,
      "height": 40,
      "fillStyle": "solid",
      "fillColor": "#ffd43b",
      "strokeColor": "#1a1a1a",
      "strokeWidth": 2
    },
    {
      "id": "text_step1",
      "type": "text",
      "x": 100,
      "y": 210,
      "text": "转为",
      "fontSize": 10,
      "fontFamily": 1,
      "textAlign": "center",
      "verticalAlign": "middle",
      "strokeColor": "#1a1a1a",
      "backgroundColor": "transparent"
    },
    {
      "id": "text_step1b",
      "type": "text",
      "x": 100,
      "y": 225,
      "text": "Candidate",
      "fontSize": 10,
      "fontFamily": 1,
      "textAlign": "center",
      "verticalAlign": "middle",
      "strokeColor": "#1a1a1a",
      "backgroundColor": "transparent"
    },
    {
      "id": "msg1",
      "type": "arrow",
      "x": 100,
      "y": 260,
      "points": [[0, 0], [150, 0]],
      "strokeColor": "#1a1a1a",
      "strokeWidth": 2
    },
    {
      "id": "text_msg1",
      "type": "text",
      "x": 135,
      "y": 250,
      "text": "RequestVote(term=2)",
      "fontSize": 10,
      "fontFamily": 1,
      "textAlign": "center",
      "strokeColor": "#1a1a1a",
      "backgroundColor": "transparent"
    },
    {
      "id": "msg2",
      "type": "arrow",
      "x": 100,
      "y": 260,
      "points": [[0, 0], [300, 0]],
      "strokeColor": "#1a1a1a",
      "strokeWidth": 2
    },
    {
      "id": "text_msg2",
      "type": "text",
      "x": 210,
      "y": 250,
      "text": "RequestVote(term=2)",
      "fontSize": 10,
      "fontFamily": 1,
      "textAlign": "center",
      "strokeColor": "#1a1a1a",
      "backgroundColor": "transparent"
    },
    {
      "id": "msg3",
      "type": "arrow",
      "x": 100,
      "y": 260,
      "points": [[0, 0], [450, 0]],
      "strokeColor": "#1a1a1a",
      "strokeWidth": 2
    },
    {
      "id": "text_msg3",
      "type": "text",
      "x": 285,
      "y": 250,
      "text": "RequestVote(term=2)",
      "fontSize": 10,
      "fontFamily": 1,
      "textAlign": "center",
      "strokeColor": "#1a1a1a",
      "backgroundColor": "transparent"
    },
    {
      "id": "ack1",
      "type": "arrow",
      "x": 250,
      "y": 290,
      "points": [[0, 0], [-150, 0]],
      "strokeColor": "#1a1a1a",
      "strokeWidth": 2
    },
    {
      "id": "text_ack1",
      "type": "text",
      "x": 210,
      "y": 280,
      "text": "Vote Granted",
      "fontSize": 10,
      "fontFamily": 1,
      "textAlign": "center",
      "strokeColor": "#2f9e44",
      "backgroundColor": "transparent"
    },
    {
      "id": "ack2",
      "type": "arrow",
      "x": 400,
      "y": 290,
      "points": [[0, 0], [-300, 0]],
      "strokeColor": "#1a1a1a",
      "strokeWidth": 2
    },
    {
      "id": "text_ack2",
      "type": "text",
      "x": 285,
      "y": 280,
      "text": "Vote Granted",
      "fontSize": 10,
      "fontFamily": 1,
      "textAlign": "center",
      "strokeColor": "#2f9e44",
      "backgroundColor": "transparent"
    },
    {
      "id": "ack3",
      "type": "arrow",
      "x": 550,
      "y": 290,
      "points": [[0, 0], [-450, 0]],
      "strokeColor": "#1a1a1a",
      "strokeWidth": 2
    },
    {
      "id": "text_ack3",
      "type": "text",
      "x": 435,
      "y": 280,
      "text": "Vote Granted",
      "fontSize": 10,
      "fontFamily": 1,
      "textAlign": "center",
      "strokeColor": "#2f9e44",
      "backgroundColor": "transparent"
    },
    {
      "id": "step2",
      "type": "rectangle",
      "x": 60,
      "y": 310,
      "width": 80,
      "height": 40,
      "fillStyle": "solid",
      "fillColor": "#2f9e44",
      "strokeColor": "#1a1a1a",
      "strokeWidth": 2
    },
    {
      "id": "text_step2",
      "type": "text",
      "x": 100,
      "y": 320,
      "text": "赢得选举",
      "fontSize": 11,
      "fontFamily": 1,
      "textAlign": "center",
      "verticalAlign": "middle",
      "strokeColor": "#ffffff",
      "backgroundColor": "transparent"
    },
    {
      "id": "text_step2b",
      "type": "text",
      "x": 100,
      "y": 335,
      "text": "成为 Leader",
      "fontSize": 11,
      "fontFamily": 1,
      "textAlign": "center",
      "verticalAlign": "middle",
      "strokeColor": "#ffffff",
      "backgroundColor": "transparent"
    },
    {
      "id": "msg4",
      "type": "arrow",
      "x": 100,
      "y": 370,
      "points": [[0, 0], [150, 0]],
      "strokeColor": "#1a1a1a",
      "strokeWidth": 2
    },
    {
      "id": "text_msg4",
      "type": "text",
      "x": 135,
      "y": 360,
      "text": "心跳",
      "fontSize": 10,
      "fontFamily": 1,
      "textAlign": "center",
      "strokeColor": "#1971c7",
      "backgroundColor": "transparent"
    },
    {
      "id": "msg5",
      "type": "arrow",
      "x": 100,
      "y": 370,
      "points": [[0, 0], [300, 0]],
      "strokeColor": "#1a1a1a",
      "strokeWidth": 2
    },
    {
      "id": "msg6",
      "type": "arrow",
      "x": 100,
      "y": 370,
      "points": [[0, 0], [450, 0]],
      "strokeColor": "#1a1a1a",
      "strokeWidth": 2
    },
    {
      "id": "box_votes",
      "type": "rectangle",
      "x": 620,
      "y": 100,
      "width": 120,
      "height": 140,
      "fillStyle": "solid",
      "fillColor": "#fff9db",
      "strokeColor": "#1a1a1a",
      "strokeWidth": 2
    },
    {
      "id": "text_votes_title",
      "type": "text",
      "x": 680,
      "y": 115,
      "text": "投票统计",
      "fontSize": 14,
      "fontFamily": 1,
      "textAlign": "center",
      "verticalAlign": "middle",
      "strokeColor": "#f08c00",
      "backgroundColor": "transparent"
    },
    {
      "id": "text_votes",
      "type": "text",
      "x": 630,
      "y": 145,
      "text": "收到票数：\n• Node-A: 1票\n• Node-B: 1票\n• Node-C: 1票\n• Node-D: 0票\n\nNode-A 获得3票\n(含自身)，赢得选举",
      "fontSize": 10,
      "fontFamily": 1,
      "textAlign": "left",
      "strokeColor": "#1a1a1a",
      "backgroundColor": "transparent"
    },
    {
      "id": "box_rules",
      "type": "rectangle",
      "x": 30,
      "y": 500,
      "width": 620,
      "height": 100,
      "fillStyle": "hachure",
      "fillColor": "#e7f5ff",
      "strokeColor": "#1971c7",
      "strokeWidth": 2
    },
    {
      "id": "text_rules_title",
      "type": "text",
      "x": 40,
      "y": 515,
      "text": "选举规则",
      "fontSize": 14,
      "fontFamily": 1,
      "textAlign": "left",
      "strokeColor": "#1971c7",
      "backgroundColor": "transparent"
    },
    {
      "id": "text_rules",
      "type": "text",
      "x": 40,
      "y": 545,
      "text": "1. 选举超时：Follower 在随机超时时间内未收到心跳，转变为 Candidate\n2. 投票限制：每个任期只能投一票，优先给日志更完整的候选人\n3. 多数派：获得集群多数节点（含自身）的投票才能成为 Leader",
      "fontSize": 11,
      "fontFamily": 1,
      "textAlign": "left",
      "strokeColor": "#1a1a1a",
      "backgroundColor": "transparent"
    }
  ],
  "appState": {
    "gridSize": null,
    "viewBackgroundColor": "#ffffff"
  }
}
